pancham/__init__.py
pancham/__main__.py
pancham/data_frame_configuration.py
pancham/data_frame_configuration_loader.py
pancham/data_frame_field.py
pancham/data_frame_loader.py
pancham/file_loader.py
pancham/file_loader_configuration.py
pancham/output_configuration.py
pancham/pancham_configuration.py
pancham/reporter.py
pancham/runner.py
pancham/validation_field.py
pancham/configuration/__init__.py
pancham/configuration/concat_field_parser.py
pancham/configuration/database_fixed_field_parser.py
pancham/configuration/database_match_field_parser.py
pancham/configuration/database_multi_field_search_parser.py
pancham/configuration/datetime_field_parser.py
pancham/configuration/deduplicate_field_parser.py
pancham/configuration/dynamic_field_parser.py
pancham/configuration/email_regex_match_parser.py
pancham/configuration/explode_field_parser.py
pancham/configuration/field_parser.py
pancham/configuration/fillnan_field_parser.py
pancham/configuration/match_field_parser.py
pancham/configuration/number_format_field_parser.py
pancham/configuration/part_text_extractor_parser.py
pancham/configuration/regex_extract_field_parser.py
pancham/configuration/regex_match_field_parser.py
pancham/configuration/remove_field_parser.py
pancham/configuration/sf_lookup_field_parser.py
pancham/configuration/split_field_parser.py
pancham/configuration/static_field_parser.py
pancham/configuration/text_field_parser.py
pancham/configuration/to_bool_field_parser.py
pancham/configuration/to_int_field_parser.py
pancham/database/__init__.py
pancham/database/caching_database_search.py
pancham/database/database_engine.py
pancham/database/database_output.py
pancham/database/database_search_manager.py
pancham/database/multi_column_database_search.py
pancham/database/phone_database_search.py
pancham/database/populating_database_search.py
pancham/database/py_database_cache_search.py
pancham/database/sql_file_loader.py
pancham/integration/__init__.py
pancham/integration/salesforce_connection.py
pancham-0.29.0.dist-info/licenses/LICENSE
pancham-0.29.0.dist-info/METADATA
pancham-0.29.0.dist-info/WHEEL
pancham-0.29.0.dist-info/entry_points.txt
pancham-0.29.0.dist-info/top_level.txt
pancham-0.29.0.dist-info/RECORD
