Metadata-Version: 2.4
Name: pancham
Version: 0.29.0
Project-URL: Homepage, https://github.com/Loqui-Tech/pancham
Requires-Python: >=3.11
License-File: LICENSE
Requires-Dist: numpy>=2.2.0
Requires-Dist: openpyxl>=3.1.0
Requires-Dist: pandas>=2.0.0
Requires-Dist: pandera>=0.20.0
Requires-Dist: SQLAlchemy>=2.0.0
Requires-Dist: pyyaml
Requires-Dist: typer
Requires-Dist: python-benedict
Requires-Dist: halo
Requires-Dist: async-typer
Requires-Dist: phonenumbers
Requires-Dist: jsonstraw>=0.1.3
Requires-Dist: simple_salesforce>=1.12.6
Requires-Dist: dask>=2025.7.0
Requires-Dist: pyarrow
Dynamic: license-file
